self_documenting_f_string/__init__.py
self_documenting_f_string/f_string_rule.py
self_documenting_f_strings/__init__.py
self_documenting_f_strings/f_string_rule.py
flake8_self_documenting_f_strings-0.1.2.dist-info/METADATA
flake8_self_documenting_f_strings-0.1.2.dist-info/WHEEL
flake8_self_documenting_f_strings-0.1.2.dist-info/entry_points.txt
flake8_self_documenting_f_strings-0.1.2.dist-info/top_level.txt
flake8_self_documenting_f_strings-0.1.2.dist-info/RECORD
